
[
    {
        "_id": {
            "$oid": "61a0834ef472290044aad1af"
        },
        "creator": "19",
        "created_date": "2021-11-26T06:48:45.842Z",
        "provenance": {
            "image": {
                "slide": "914"
            },
            "analysis": {
                "source": "human",
                "execution_id": "_4n6z4y8di",
                "name": "High NC",
                "labelId": "_t0aj89nsw",
                "type": "label"
            }
        },
        "properties": {
            "annotations": {
                "id": "_4n6z4y8di",
                "labelId": "_t0aj89nsw",
                "name": "High NC",
                "notes": "High NC"
            }
        },
        "geometries": {
            "type": "FeatureCollection",
            "features": [
                {
                    "type": "Feature",
                    "properties": {
                        "style": {
                            "color": "#00d1ff",
                            "lineJoin": "round",
                            "lineCap": "round",
                            "isFill": true
                        },
                        "area": 87637.83789600001,
                        "circumference": 1113.474230253374
                    },
                    "geometry": {
                        "type": "Polygon",
                        "coordinates": [
                            [
                                [
                                    0.4104781177817297,
                                    0.49535315985130113
                                ],
                                [
                                    0.4095991496494348,
                                    0.4945450137384839
                                ],
                                [
                                    0.4036916661556387,
                                    0.4927266849846452
                                ],
                                [
                                    0.401116085116821,
                                    0.49171650234362374
                                ],
                                [
                                    0.3986835919134932,
                                    0.4912316146759334
                                ],
                                [
                                    0.3941456634165287,
                                    0.49113059641183127
                                ],
                                [
                                    0.39277610841969707,
                                    0.4925852594149022
                                ],
                                [
                                    0.38887185462275914,
                                    0.4976361726200097
                                ],
                                [
                                    0.38876964902598066,
                                    0.49797963471795703
                                ],
                                [
                                    0.38844259111628954,
                                    0.505313560691773
                                ],
                                [
                                    0.38819729768402117,
                                    0.5063237433327946
                                ],
                                [
                                    0.387604505222706,
                                    0.5119605624696946
                                ],
                                [
                                    0.3870117127613908,
                                    0.5138799094876354
                                ],
                                [
                                    0.38692994828396804,
                                    0.5156780345886536
                                ],
                                [
                                    0.38721612395494776,
                                    0.5169710683691612
                                ],
                                [
                                    0.3877475930581959,
                                    0.5181832875383869
                                ],
                                [
                                    0.3889740602195376,
                                    0.5198601907224826
                                ],
                                [
                                    0.3959853641585413,
                                    0.520062227250687
                                ],
                                [
                                    0.4015044663845792,
                                    0.5173549377727493
                                ],
                                [
                                    0.4074528321170867,
                                    0.5150921286568612
                                ],
                                [
                                    0.4106212056172196,
                                    0.5130717633748182
                                ],
                                [
                                    0.411602379346293,
                                    0.5076167771133021
                                ],
                                [
                                    0.41180679053985,
                                    0.5038588976887021
                                ],
                                [
                                    0.41082561681077656,
                                    0.4987069662194925
                                ],
                                [
                                    0.4106212056172196,
                                    0.4966259899789882
                                ],
                                [
                                    0.4106825289752867,
                                    0.49565621464360754
                                ],
                                [
                                    0.4104781177817297,
                                    0.49535315985130113
                                ]
                            ]
                        ]
                    },
                    "bound": {
                        "type": "Polygon",
                        "coordinates": [
                            [
                                [
                                    0.38692994828396804,
                                    0.49113059641183127
                                ],
                                [
                                    0.41180679053985,
                                    0.49113059641183127
                                ],
                                [
                                    0.41180679053985,
                                    0.520062227250687
                                ],
                                [
                                    0.38692994828396804,
                                    0.520062227250687
                                ],
                                [
                                    0.38692994828396804,
                                    0.49113059641183127
                                ]
                            ]
                        ]
                    }
                }
            ]
        }
    },
    {
        "_id": {
            "$oid": "61a0840df472290044aad1df"
        },
        "creator": "19",
        "created_date": "2021-11-26T06:51:57.196Z",
        "provenance": {
            "image": {
                "slide": "914"
            },
            "analysis": {
                "source": "human",
                "execution_id": "_6h54dfe42",
                "name": "High NC",
                "labelId": "_t0aj89nsw",
                "type": "label"
            }
        },
        "properties": {
            "annotations": {
                "id": "_6h54dfe42",
                "labelId": "_t0aj89nsw",
                "name": "High NC",
                "notes": "High NC"
            }
        },
        "geometries": {
            "type": "FeatureCollection",
            "features": [
                {
                    "type": "Feature",
                    "properties": {
                        "style": {
                            "color": "#00d1ff",
                            "lineJoin": "round",
                            "lineCap": "round",
                            "isFill": true
                        },
                        "area": 136485.940248,
                        "circumference": 1329.865243773889
                    },
                    "geometry": {
                        "type": "Polygon",
                        "coordinates": [
                            [
                                [
                                    0.8892500153308395,
                                    0.8838087926297075
                                ],
                                [
                                    0.8864495819791092,
                                    0.8830006465168903
                                ],
                                [
                                    0.8803990106498232,
                                    0.882798609988686
                                ],
                                [
                                    0.8746141738721612,
                                    0.8839704218522709
                                ],
                                [
                                    0.8710983013429815,
                                    0.8863140455794407
                                ],
                                [
                                    0.8687066903783651,
                                    0.8888799094876354
                                ],
                                [
                                    0.8662128738169702,
                                    0.8932034911912073
                                ],
                                [
                                    0.8661719915782589,
                                    0.8935065459835139
                                ],
                                [
                                    0.8654974346395209,
                                    0.8946783578470987
                                ],
                                [
                                    0.8646389076265816,
                                    0.8970825925327299
                                ],
                                [
                                    0.8642300852394678,
                                    0.8987999030224665
                                ],
                                [
                                    0.8638212628523538,
                                    0.9018506545983513
                                ],
                                [
                                    0.8642300852394678,
                                    0.9030224664619363
                                ],
                                [
                                    0.8669283129944195,
                                    0.9068409568449975
                                ],
                                [
                                    0.8684613969460968,
                                    0.9088007111685793
                                ],
                                [
                                    0.873019766562417,
                                    0.9132657184418943
                                ],
                                [
                                    0.8751252018560537,
                                    0.9143769193470179
                                ],
                                [
                                    0.8786819566239448,
                                    0.915084047195733
                                ],
                                [
                                    0.8800515116207763,
                                    0.9154881202521415
                                ],
                                [
                                    0.88559105496617,
                                    0.9154275092936803
                                ],
                                [
                                    0.889822366672799,
                                    0.915084047195733
                                ],
                                [
                                    0.891702949653523,
                                    0.9141748828188136
                                ],
                                [
                                    0.8941354428568509,
                                    0.9125181832875384
                                ],
                                [
                                    0.8949939698697901,
                                    0.9116696298690803
                                ],
                                [
                                    0.8950961754665685,
                                    0.9111645385485696
                                ],
                                [
                                    0.8958116146440179,
                                    0.9097502828511395
                                ],
                                [
                                    0.8970380818053597,
                                    0.9059317924680782
                                ],
                                [
                                    0.8976513153860305,
                                    0.9032649102957815
                                ],
                                [
                                    0.8978966088182989,
                                    0.8990019395506708
                                ],
                                [
                                    0.8978966088182989,
                                    0.8954663003070955
                                ],
                                [
                                    0.8953619100181925,
                                    0.8901931469209633
                                ],
                                [
                                    0.8946464708407432,
                                    0.887829319540973
                                ],
                                [
                                    0.8929089756955091,
                                    0.8850210117989332
                                ],
                                [
                                    0.8919482430857913,
                                    0.8841118474220139
                                ],
                                [
                                    0.891641626295456,
                                    0.8839704218522709
                                ],
                                [
                                    0.8899654545082889,
                                    0.8838694035881688
                                ],
                                [
                                    0.8897201610760205,
                                    0.8837683853240665
                                ],
                                [
                                    0.8892500153308395,
                                    0.8838087926297075
                                ]
                            ]
                        ]
                    },
                    "bound": {
                        "type": "Polygon",
                        "coordinates": [
                            [
                                [
                                    0.8638212628523538,
                                    0.882798609988686
                                ],
                                [
                                    0.8978966088182989,
                                    0.882798609988686
                                ],
                                [
                                    0.8978966088182989,
                                    0.9154881202521415
                                ],
                                [
                                    0.8638212628523538,
                                    0.9154881202521415
                                ],
                                [
                                    0.8638212628523538,
                                    0.882798609988686
                                ]
                            ]
                        ]
                    }
                }
            ]
        }
    },
    {
        "_id": {
            "$oid": "61a082b0fdadca004589e871"
        },
        "creator": "19",
        "created_date": "2021-11-26T06:46:08.225Z",
        "provenance": {
            "image": {
                "slide": "914"
            },
            "analysis": {
                "source": "human",
                "execution_id": "_7uvuqhbjj",
                "name": "High NC",
                "labelId": "_t0aj89nsw",
                "type": "label"
            }
        },
        "properties": {
            "annotations": {
                "id": "_7uvuqhbjj",
                "labelId": "_t0aj89nsw",
                "name": "High NC",
                "notes": "High NC"
            }
        },
        "geometries": {
            "type": "FeatureCollection",
            "features": [
                {
                    "type": "Feature",
                    "properties": {
                        "style": {
                            "color": "#00d1ff",
                            "lineJoin": "round",
                            "lineCap": "round",
                            "isFill": true
                        },
                        "area": 56885.67662400001,
                        "circumference": 900.4651794479984
                    },
                    "geometry": {
                        "type": "Polygon",
                        "coordinates": [
                            [
                                [
                                    0.4587191594611721,
                                    0.2539195086471634
                                ],
                                [
                                    0.4576153390159645,
                                    0.25387910134152253
                                ],
                                [
                                    0.4554485803642607,
                                    0.2541619524810086
                                ],
                                [
                                    0.4526481470125304,
                                    0.25509132051074834
                                ],
                                [
                                    0.45146256208990004,
                                    0.2557176337481817
                                ],
                                [
                                    0.4511763864189203,
                                    0.25618231776305156
                                ],
                                [
                                    0.44882565769301525,
                                    0.258788588976887
                                ],
                                [
                                    0.4471290447864925,
                                    0.2615564894132859
                                ],
                                [
                                    0.44580037202837225,
                                    0.26555681267173104
                                ],
                                [
                                    0.44573904867030517,
                                    0.26717310489736545
                                ],
                                [
                                    0.44590257762515073,
                                    0.2691934701794084
                                ],
                                [
                                    0.4466180168026001,
                                    0.27238564732503634
                                ],
                                [
                                    0.4467202223993786,
                                    0.27347664457733956
                                ],
                                [
                                    0.4466588990413115,
                                    0.27388071763374816
                                ],
                                [
                                    0.44725169150262667,
                                    0.27499191853887184
                                ],
                                [
                                    0.44778316060587475,
                                    0.2766082107645062
                                ],
                                [
                                    0.4486621287381697,
                                    0.27844674317116536
                                ],
                                [
                                    0.4493571267962634,
                                    0.2793761112009051
                                ],
                                [
                                    0.4520553545512152,
                                    0.28111362534346207
                                ],
                                [
                                    0.452811675967376,
                                    0.28139647648294813
                                ],
                                [
                                    0.4556734326771734,
                                    0.2819823824147406
                                ],
                                [
                                    0.45591872610944173,
                                    0.2819217714562793
                                ],
                                [
                                    0.45884180617730624,
                                    0.28002262809115885
                                ],
                                [
                                    0.45953680423539994,
                                    0.2792144819783417
                                ],
                                [
                                    0.4601909200547822,
                                    0.27763859705834815
                                ],
                                [
                                    0.4615400339322581,
                                    0.27567884273476645
                                ],
                                [
                                    0.4620715030355062,
                                    0.27458784548246323
                                ],
                                [
                                    0.462827824451667,
                                    0.27244625828349767
                                ],
                                [
                                    0.4631140001226467,
                                    0.2681024729271052
                                ],
                                [
                                    0.4621123852742176,
                                    0.2624858574430257
                                ],
                                [
                                    0.4608859181128759,
                                    0.2573945369322774
                                ],
                                [
                                    0.46025224341284926,
                                    0.25664700177792144
                                ],
                                [
                                    0.45906665849021894,
                                    0.25410134152254726
                                ],
                                [
                                    0.4587191594611721,
                                    0.2539195086471634
                                ]
                            ]
                        ]
                    },
                    "bound": {
                        "type": "Polygon",
                        "coordinates": [
                            [
                                [
                                    0.44573904867030517,
                                    0.25387910134152253
                                ],
                                [
                                    0.4631140001226467,
                                    0.25387910134152253
                                ],
                                [
                                    0.4631140001226467,
                                    0.2819823824147406
                                ],
                                [
                                    0.44573904867030517,
                                    0.2819823824147406
                                ],
                                [
                                    0.44573904867030517,
                                    0.25387910134152253
                                ]
                            ]
                        ]
                    }
                }
            ]
        }
    },
    {
        "_id": {
            "$oid": "61a082ea5860ed0051a1cf24"
        },
        "creator": "19",
        "created_date": "2021-11-26T06:47:06.526Z",
        "provenance": {
            "image": {
                "slide": "914"
            },
            "analysis": {
                "source": "human",
                "execution_id": "_as5y9al73",
                "name": "High NC",
                "labelId": "_t0aj89nsw",
                "type": "label"
            }
        },
        "properties": {
            "annotations": {
                "id": "_as5y9al73",
                "labelId": "_t0aj89nsw",
                "name": "High NC",
                "notes": "High NC"
            }
        },
        "geometries": {
            "type": "FeatureCollection",
            "features": [
                {
                    "type": "Feature",
                    "properties": {
                        "style": {
                            "color": "#00d1ff",
                            "lineJoin": "round",
                            "lineCap": "round",
                            "isFill": true
                        },
                        "area": 149684.040072,
                        "circumference": 1433.0773357432327
                    },
                    "geometry": {
                        "type": "Polygon",
                        "coordinates": [
                            [
                                [
                                    0.4347212853375851,
                                    0.35707935994827866
                                ],
                                [
                                    0.4273011590114675,
                                    0.3554226604170034
                                ],
                                [
                                    0.4241941088694017,
                                    0.3549579764021335
                                ],
                                [
                                    0.4166513358271499,
                                    0.35552367868110557
                                ],
                                [
                                    0.4126039941947221,
                                    0.3565136576693066
                                ],
                                [
                                    0.40383475399112856,
                                    0.35992807499595925
                                ],
                                [
                                    0.40119784959424376,
                                    0.36142314530467107
                                ],
                                [
                                    0.3998487357167679,
                                    0.36356473250363663
                                ],
                                [
                                    0.39896976758447295,
                                    0.3658275416195248
                                ],
                                [
                                    0.39755933034892993,
                                    0.37160578632616775
                                ],
                                [
                                    0.39943991332965395,
                                    0.3771011798933247
                                ],
                                [
                                    0.4006050571329286,
                                    0.37964684014869887
                                ],
                                [
                                    0.4016066719813577,
                                    0.3808590593179247
                                ],
                                [
                                    0.40213814108460577,
                                    0.3816874090835623
                                ],
                                [
                                    0.4046523987653564,
                                    0.3830612574753515
                                ],
                                [
                                    0.40786165450420064,
                                    0.3845765314368838
                                ],
                                [
                                    0.41037591218495123,
                                    0.3852634556327784
                                ],
                                [
                                    0.41096870464626645,
                                    0.3852634556327784
                                ],
                                [
                                    0.4172850105271765,
                                    0.3837683853240666
                                ],
                                [
                                    0.4205760307434435,
                                    0.3831824793922741
                                ],
                                [
                                    0.43138938288260664,
                                    0.3793033780507516
                                ],
                                [
                                    0.4342102573536927,
                                    0.3776264748666559
                                ],
                                [
                                    0.4356615768279471,
                                    0.3762324228220462
                                ],
                                [
                                    0.436540544960242,
                                    0.374858574430257
                                ],
                                [
                                    0.4367858383925104,
                                    0.3741514465815419
                                ],
                                [
                                    0.4392387727151939,
                                    0.370393567156942
                                ],
                                [
                                    0.4399950941313546,
                                    0.3679085178600291
                                ],
                                [
                                    0.43940230167003946,
                                    0.3639283982544044
                                ],
                                [
                                    0.4392387727151939,
                                    0.36120090512364633
                                ],
                                [
                                    0.43882995032808,
                                    0.36045336996929045
                                ],
                                [
                                    0.4371333374215572,
                                    0.3587158558267335
                                ],
                                [
                                    0.43596819361828254,
                                    0.357847098755455
                                ],
                                [
                                    0.43525275444083317,
                                    0.3575036366575077
                                ],
                                [
                                    0.4349052554117864,
                                    0.3570389526426378
                                ],
                                [
                                    0.4347212853375851,
                                    0.35707935994827866
                                ]
                            ]
                        ]
                    },
                    "bound": {
                        "type": "Polygon",
                        "coordinates": [
                            [
                                [
                                    0.39755933034892993,
                                    0.3549579764021335
                                ],
                                [
                                    0.4399950941313546,
                                    0.3549579764021335
                                ],
                                [
                                    0.4399950941313546,
                                    0.3852634556327784
                                ],
                                [
                                    0.39755933034892993,
                                    0.3852634556327784
                                ],
                                [
                                    0.39755933034892993,
                                    0.3549579764021335
                                ]
                            ]
                        ]
                    }
                }
            ]
        }
    },
    {
        "_id": {
            "$oid": "61a083925860ed0051a1cf46"
        },
        "creator": "19",
        "created_date": "2021-11-26T06:49:54.187Z",
        "provenance": {
            "image": {
                "slide": "914"
            },
            "analysis": {
                "source": "human",
                "execution_id": "_be9lx9xvr",
                "name": "High NC",
                "labelId": "_t0aj89nsw",
                "type": "label"
            }
        },
        "properties": {
            "annotations": {
                "id": "_be9lx9xvr",
                "labelId": "_t0aj89nsw",
                "name": "High NC",
                "notes": "High NC"
            }
        },
        "geometries": {
            "type": "FeatureCollection",
            "features": [
                {
                    "type": "Feature",
                    "properties": {
                        "style": {
                            "color": "#00d1ff",
                            "lineJoin": "round",
                            "lineCap": "round",
                            "isFill": true
                        },
                        "area": 105138.682992,
                        "circumference": 1216.0030622482147
                    },
                    "geometry": {
                        "type": "Polygon",
                        "coordinates": [
                            [
                                [
                                    0.6064266879254308,
                                    0.5718441894294488
                                ],
                                [
                                    0.6029721387543182,
                                    0.5704703410376596
                                ],
                                [
                                    0.5975348010057031,
                                    0.5697228058833037
                                ],
                                [
                                    0.5971259786185892,
                                    0.5694399547438177
                                ],
                                [
                                    0.5947956910120398,
                                    0.5685711976725392
                                ],
                                [
                                    0.5901146746795854,
                                    0.5676418296427994
                                ],
                                [
                                    0.5880501216246602,
                                    0.5675812186843381
                                ],
                                [
                                    0.5840845444696552,
                                    0.5687328268951026
                                ],
                                [
                                    0.581141023282435,
                                    0.5698440278002262
                                ],
                                [
                                    0.5795670570920464,
                                    0.5712784871504768
                                ],
                                [
                                    0.5775229451564767,
                                    0.5738847583643123
                                ],
                                [
                                    0.5761738312790008,
                                    0.5759051236463553
                                ],
                                [
                                    0.5755810388176856,
                                    0.5770163245514789
                                ],
                                [
                                    0.5747633940434578,
                                    0.5817035720058187
                                ],
                                [
                                    0.5748247174015249,
                                    0.5866130596411832
                                ],
                                [
                                    0.5742932482982768,
                                    0.5883505737837401
                                ],
                                [
                                    0.5749473641176591,
                                    0.5924519153062874
                                ],
                                [
                                    0.5757036855338198,
                                    0.5932600614191046
                                ],
                                [
                                    0.5772367694854971,
                                    0.5940278002262809
                                ],
                                [
                                    0.5810388176856565,
                                    0.5949369646032002
                                ],
                                [
                                    0.5902782036344311,
                                    0.5929772102796186
                                ],
                                [
                                    0.59303775474745,
                                    0.5915831582350088
                                ],
                                [
                                    0.5952453956378652,
                                    0.5907750121221917
                                ],
                                [
                                    0.6036875779317675,
                                    0.5868352998222078
                                ],
                                [
                                    0.6047300750189081,
                                    0.5860271537093906
                                ],
                                [
                                    0.6055477197931358,
                                    0.5844108614837563
                                ],
                                [
                                    0.6068355103125447,
                                    0.5808954258930015
                                ],
                                [
                                    0.6072034504609473,
                                    0.5783497656376273
                                ],
                                [
                                    0.6071421271028802,
                                    0.5758445126878939
                                ],
                                [
                                    0.6068968336706118,
                                    0.5726725391950864
                                ],
                                [
                                    0.6067946280738333,
                                    0.5721472442217553
                                ],
                                [
                                    0.6064266879254308,
                                    0.5718441894294488
                                ]
                            ]
                        ]
                    },
                    "bound": {
                        "type": "Polygon",
                        "coordinates": [
                            [
                                [
                                    0.5742932482982768,
                                    0.5675812186843381
                                ],
                                [
                                    0.6072034504609473,
                                    0.5675812186843381
                                ],
                                [
                                    0.6072034504609473,
                                    0.5949369646032002
                                ],
                                [
                                    0.5742932482982768,
                                    0.5949369646032002
                                ],
                                [
                                    0.5742932482982768,
                                    0.5675812186843381
                                ]
                            ]
                        ]
                    }
                }
            ]
        }
    },
    {
        "_id": {
            "$oid": "61a0832ff472290044aad1a5"
        },
        "creator": "19",
        "created_date": "2021-11-26T06:48:14.978Z",
        "provenance": {
            "image": {
                "slide": "914"
            },
            "analysis": {
                "source": "human",
                "execution_id": "_k6qbc81a6",
                "name": "High NC",
                "labelId": "_t0aj89nsw",
                "type": "label"
            }
        },
        "properties": {
            "annotations": {
                "id": "_k6qbc81a6",
                "labelId": "_t0aj89nsw",
                "name": "High NC",
                "notes": "High NC"
            }
        },
        "geometries": {
            "type": "FeatureCollection",
            "features": [
                {
                    "type": "Feature",
                    "properties": {
                        "style": {
                            "color": "#00d1ff",
                            "lineJoin": "round",
                            "lineCap": "round",
                            "isFill": true
                        },
                        "area": 174202.17242400002,
                        "circumference": 1570.7364524635493
                    },
                    "geometry": {
                        "type": "Polygon",
                        "coordinates": [
                            [
                                [
                                    0.681977065064083,
                                    0.38393001454663
                                ],
                                [
                                    0.6819157417060159,
                                    0.38380879262970746
                                ],
                                [
                                    0.676928108583226,
                                    0.38144496524971716
                                ],
                                [
                                    0.6726354735185299,
                                    0.3805358008727978
                                ],
                                [
                                    0.6715929764313894,
                                    0.3800509132051075
                                ],
                                [
                                    0.66147462235032,
                                    0.37887910134152253
                                ],
                                [
                                    0.65031377118211,
                                    0.3797074511071602
                                ],
                                [
                                    0.6405429161300873,
                                    0.3902537578794246
                                ],
                                [
                                    0.6408904151591341,
                                    0.3939308226927428
                                ],
                                [
                                    0.6431389382882606,
                                    0.4017092290286084
                                ],
                                [
                                    0.6449581979109176,
                                    0.4047599806044933
                                ],
                                [
                                    0.6463686351464606,
                                    0.4066389203167933
                                ],
                                [
                                    0.65031377118211,
                                    0.4141344755131728
                                ],
                                [
                                    0.6526236176693035,
                                    0.4167811540326491
                                ],
                                [
                                    0.6545246417693833,
                                    0.4173266526588007
                                ],
                                [
                                    0.6573250751211136,
                                    0.41781154032649104
                                ],
                                [
                                    0.65985977392122,
                                    0.41781154032649104
                                ],
                                [
                                    0.6638662333149363,
                                    0.41587198965572975
                                ],
                                [
                                    0.6685063674086793,
                                    0.4139324389849685
                                ],
                                [
                                    0.673902822918583,
                                    0.40552771941166965
                                ],
                                [
                                    0.6744751742605425,
                                    0.40498222078551804
                                ],
                                [
                                    0.6744751742605425,
                                    0.404557944076289
                                ],
                                [
                                    0.6755994358251057,
                                    0.40179004363989007
                                ],
                                [
                                    0.6781136935058564,
                                    0.3939308226927428
                                ],
                                [
                                    0.6808528034995196,
                                    0.38720300630353965
                                ],
                                [
                                    0.6812003025285664,
                                    0.3852634556327784
                                ],
                                [
                                    0.681977065064083,
                                    0.38393001454663
                                ]
                            ]
                        ]
                    },
                    "bound": {
                        "type": "Polygon",
                        "coordinates": [
                            [
                                [
                                    0.6405429161300873,
                                    0.37887910134152253
                                ],
                                [
                                    0.681977065064083,
                                    0.37887910134152253
                                ],
                                [
                                    0.681977065064083,
                                    0.41781154032649104
                                ],
                                [
                                    0.6405429161300873,
                                    0.41781154032649104
                                ],
                                [
                                    0.6405429161300873,
                                    0.37887910134152253
                                ]
                            ]
                        ]
                    }
                }
            ]
        }
    },
    {
        "_id": {
            "$oid": "61a08382fdadca004589e89d"
        },
        "creator": "19",
        "created_date": "2021-11-26T06:49:37.645Z",
        "provenance": {
            "image": {
                "slide": "914"
            },
            "analysis": {
                "source": "human",
                "execution_id": "_o28sddgac",
                "name": "High NC",
                "labelId": "_t0aj89nsw",
                "type": "label"
            }
        },
        "properties": {
            "annotations": {
                "id": "_o28sddgac",
                "labelId": "_t0aj89nsw",
                "name": "High NC",
                "notes": "High NC"
            }
        },
        "geometries": {
            "type": "FeatureCollection",
            "features": [
                {
                    "type": "Feature",
                    "properties": {
                        "style": {
                            "color": "#00d1ff",
                            "lineJoin": "round",
                            "lineCap": "round",
                            "isFill": true
                        },
                        "area": 76863.84451200001,
                        "circumference": 1001.0545127346187
                    },
                    "geometry": {
                        "type": "Polygon",
                        "coordinates": [
                            [
                                [
                                    0.6400727703849063,
                                    0.5352149668660093
                                ],
                                [
                                    0.6388463032235645,
                                    0.5341845805721674
                                ],
                                [
                                    0.6352691073363177,
                                    0.5324470664296105
                                ],
                                [
                                    0.6321824983136076,
                                    0.5314166801357686
                                ],
                                [
                                    0.6319372048813393,
                                    0.5312348472603847
                                ],
                                [
                                    0.6310582367490444,
                                    0.5311338289962825
                                ],
                                [
                                    0.6267247194456368,
                                    0.5310732180378213
                                ],
                                [
                                    0.6232088469164572,
                                    0.5321036043316631
                                ],
                                [
                                    0.6225138488583635,
                                    0.532851139486019
                                ],
                                [
                                    0.6221050264712495,
                                    0.5334976563762728
                                ],
                                [
                                    0.6205923836389281,
                                    0.5363261677711331
                                ],
                                [
                                    0.6193454753582306,
                                    0.5382455147890739
                                ],
                                [
                                    0.6189366529711167,
                                    0.5396193631808631
                                ],
                                [
                                    0.618650477300137,
                                    0.5430337805075157
                                ],
                                [
                                    0.6188344473743382,
                                    0.547559398739292
                                ],
                                [
                                    0.6201222378937471,
                                    0.5497615968967189
                                ],
                                [
                                    0.6253347233294495,
                                    0.5547316954905447
                                ],
                                [
                                    0.6280125099650457,
                                    0.5562873767577178
                                ],
                                [
                                    0.6317532348071381,
                                    0.5576814288023274
                                ],
                                [
                                    0.6351669017395393,
                                    0.5578430580248909
                                ],
                                [
                                    0.6378446883751354,
                                    0.5556004525618232
                                ],
                                [
                                    0.6401340937429734,
                                    0.5531154032649103
                                ],
                                [
                                    0.6415445309785164,
                                    0.5501656699531275
                                ],
                                [
                                    0.6423621757527442,
                                    0.5476200096977534
                                ],
                                [
                                    0.6423621757527442,
                                    0.5455390334572491
                                ],
                                [
                                    0.6420146767236974,
                                    0.5390536609018911
                                ],
                                [
                                    0.6410743852333354,
                                    0.537316146759334
                                ],
                                [
                                    0.6405429161300873,
                                    0.5365686116049782
                                ],
                                [
                                    0.6400727703849063,
                                    0.5355180216583159
                                ],
                                [
                                    0.6400727703849063,
                                    0.5352149668660093
                                ]
                            ]
                        ]
                    },
                    "bound": {
                        "type": "Polygon",
                        "coordinates": [
                            [
                                [
                                    0.618650477300137,
                                    0.5310732180378213
                                ],
                                [
                                    0.6423621757527442,
                                    0.5310732180378213
                                ],
                                [
                                    0.6423621757527442,
                                    0.5578430580248909
                                ],
                                [
                                    0.618650477300137,
                                    0.5578430580248909
                                ],
                                [
                                    0.618650477300137,
                                    0.5310732180378213
                                ]
                            ]
                        ]
                    }
                }
            ]
        }
    },
    {
        "_id": {
            "$oid": "61a0831efdadca004589e887"
        },
        "creator": "19",
        "created_date": "2021-11-26T06:47:57.963Z",
        "provenance": {
            "image": {
                "slide": "914"
            },
            "analysis": {
                "source": "human",
                "execution_id": "_rbhac9zec",
                "name": "High NC",
                "labelId": "_t0aj89nsw",
                "type": "label"
            }
        },
        "properties": {
            "annotations": {
                "id": "_rbhac9zec",
                "labelId": "_t0aj89nsw",
                "name": "High NC",
                "notes": "High NC"
            }
        },
        "geometries": {
            "type": "FeatureCollection",
            "features": [
                {
                    "type": "Feature",
                    "properties": {
                        "style": {
                            "color": "#00d1ff",
                            "lineJoin": "round",
                            "lineCap": "round",
                            "isFill": true
                        },
                        "area": 277371.69163200003,
                        "circumference": 1928.9546312815044
                    },
                    "geometry": {
                        "type": "Polygon",
                        "coordinates": [
                            [
                                [
                                    0.6375789538235114,
                                    0.33441086148375626
                                ],
                                [
                                    0.6365364567363709,
                                    0.33386536285760465
                                ],
                                [
                                    0.6262136914617444,
                                    0.3301882980442864
                                ],
                                [
                                    0.6215735573680015,
                                    0.32956198480685306
                                ],
                                [
                                    0.6157478383516282,
                                    0.32915791175044445
                                ],
                                [
                                    0.6113121154514422,
                                    0.32956198480685306
                                ],
                                [
                                    0.6066106579996321,
                                    0.3330976240504283
                                ],
                                [
                                    0.6027472864414055,
                                    0.3403305317601422
                                ],
                                [
                                    0.6054863964350687,
                                    0.35560449329238725
                                ],
                                [
                                    0.6075918317287055,
                                    0.36128171973492806
                                ],
                                [
                                    0.6103309417223687,
                                    0.3662922256343947
                                ],
                                [
                                    0.6131313750740991,
                                    0.36934297721027964
                                ],
                                [
                                    0.6174240101387952,
                                    0.37518183287538387
                                ],
                                [
                                    0.6180576848388217,
                                    0.37518183287538387
                                ],
                                [
                                    0.6212873816970217,
                                    0.3760707935994828
                                ],
                                [
                                    0.6285848613070052,
                                    0.37948521092613546
                                ],
                                [
                                    0.6326730851781444,
                                    0.38037417165023435
                                ],
                                [
                                    0.6344310214427342,
                                    0.38023274608049135
                                ],
                                [
                                    0.6425052635882341,
                                    0.37455551963795053
                                ],
                                [
                                    0.6451626091044745,
                                    0.37302004202359784
                                ],
                                [
                                    0.647492896711024,
                                    0.37011071601745593
                                ],
                                [
                                    0.6497414198401504,
                                    0.36350412154517536
                                ],
                                [
                                    0.6502320067046872,
                                    0.3588572813964765
                                ],
                                [
                                    0.6503546534208213,
                                    0.3542710522062389
                                ],
                                [
                                    0.6497414198401504,
                                    0.35261435267496366
                                ],
                                [
                                    0.6476155434271581,
                                    0.34831097462421207
                                ],
                                [
                                    0.6462255473109707,
                                    0.34511879747858415
                                ],
                                [
                                    0.646143782833548,
                                    0.3446339098108938
                                ],
                                [
                                    0.6450195212689847,
                                    0.3424721189591078
                                ],
                                [
                                    0.6425052635882341,
                                    0.3368555034750283
                                ],
                                [
                                    0.6422804112753214,
                                    0.3368555034750283
                                ],
                                [
                                    0.6415854132172277,
                                    0.33651204137708096
                                ],
                                [
                                    0.6387032153880746,
                                    0.33469371262324227
                                ],
                                [
                                    0.6376607183009342,
                                    0.334350250525295
                                ],
                                [
                                    0.6375789538235114,
                                    0.33441086148375626
                                ]
                            ]
                        ]
                    },
                    "bound": {
                        "type": "Polygon",
                        "coordinates": [
                            [
                                [
                                    0.6027472864414055,
                                    0.32915791175044445
                                ],
                                [
                                    0.6503546534208213,
                                    0.32915791175044445
                                ],
                                [
                                    0.6503546534208213,
                                    0.38037417165023435
                                ],
                                [
                                    0.6027472864414055,
                                    0.38037417165023435
                                ],
                                [
                                    0.6027472864414055,
                                    0.32915791175044445
                                ]
                            ]
                        ]
                    }
                }
            ]
        }
    }
]